setup.py
cht_lib/__init__.py
cht_lib/one.py
cht_lib/two.py
cht_lib.egg-info/PKG-INFO
cht_lib.egg-info/SOURCES.txt
cht_lib.egg-info/dependency_links.txt
cht_lib.egg-info/top_level.txt