Metadata-Version: 2.1
Name: cht-lib
Version: 0.0.1
Summary: My Package
Home-page: UNKNOWN
Author: Chitaev
Author-email: your@domain.com
License: UNKNOWN
Platform: UNKNOWN
